bio2bel_adeptus/__init__.py
bio2bel_adeptus/__main__.py
bio2bel_adeptus/cli.py
bio2bel_adeptus/constants.py
bio2bel_adeptus/manager.py
bio2bel_adeptus/models.py
bio2bel_adeptus/parser.py
bio2bel_adeptus-0.0.1.dist-info/LICENSE
bio2bel_adeptus-0.0.1.dist-info/METADATA
bio2bel_adeptus-0.0.1.dist-info/WHEEL
bio2bel_adeptus-0.0.1.dist-info/entry_points.txt
bio2bel_adeptus-0.0.1.dist-info/top_level.txt
bio2bel_adeptus-0.0.1.dist-info/RECORD
